pagerduty_mcp/__init__.py
pagerduty_mcp/__main__.py
pagerduty_mcp/client.py
pagerduty_mcp/server.py
pagerduty_mcp/utils.py
pagerduty_mcp/models/__init__.py
pagerduty_mcp/models/alert_grouping_settings.py
pagerduty_mcp/models/base.py
pagerduty_mcp/models/context.py
pagerduty_mcp/models/escalation_policies.py
pagerduty_mcp/models/event_orchestrations.py
pagerduty_mcp/models/incidents.py
pagerduty_mcp/models/oncalls.py
pagerduty_mcp/models/references.py
pagerduty_mcp/models/schedules.py
pagerduty_mcp/models/services.py
pagerduty_mcp/models/teams.py
pagerduty_mcp/models/users.py
pagerduty_mcp/tools/__init__.py
pagerduty_mcp/tools/alert_grouping_settings.py
pagerduty_mcp/tools/escalation_policies.py
pagerduty_mcp/tools/event_orchestrations.py
pagerduty_mcp/tools/incidents.py
pagerduty_mcp/tools/oncalls.py
pagerduty_mcp/tools/schedules.py
pagerduty_mcp/tools/services.py
pagerduty_mcp/tools/teams.py
pagerduty_mcp/tools/users.py
pagerduty_mcp_community-0.2.2b1.dist-info/licenses/LICENSE
scripts/sync_version.py
scripts/validate_server_json.py
tests/test_alert_grouping_settings.py
tests/test_escalation_policies.py
tests/test_event_orchestrations.py
tests/test_incidents.py
tests/test_oncalls.py
tests/test_schedules.py
tests/test_services.py
tests/test_teams.py
tests/test_users.py
tests/evals/__init__.py
tests/evals/competency_test.py
tests/evals/mcp_tool_tracer.py
tests/evals/run_tests.py
tests/evals/test_alert_grouping_settings.py
tests/evals/test_event_orchestrations.py
tests/evals/test_incidents.py
tests/evals/test_teams.py
tests/evals/llm_clients/__init__.py
tests/evals/llm_clients/base.py
tests/evals/llm_clients/bedrock_client.py
tests/evals/llm_clients/openai_client.py
pagerduty_mcp_community-0.2.2b1.dist-info/METADATA
pagerduty_mcp_community-0.2.2b1.dist-info/WHEEL
pagerduty_mcp_community-0.2.2b1.dist-info/entry_points.txt
pagerduty_mcp_community-0.2.2b1.dist-info/top_level.txt
pagerduty_mcp_community-0.2.2b1.dist-info/RECORD
