Metadata-Version: 2.4
Name: pagerduty-mcp-community
Version: 0.2.2b1
Summary: Community-maintained fork of PagerDuty's MCP server with additional capabilities for interacting with your PagerDuty account.
Author: PagerDuty, Community Contributors
Maintainer: Community Contributors
License: Apache-2.0
Project-URL: Homepage, https://github.com/carlyou/pagerduty-mcp-community
Project-URL: Repository, https://github.com/carlyou/pagerduty-mcp-community
Project-URL: Issue Tracker, https://github.com/carlyou/pagerduty-mcp-community/issues
Project-URL: Original Project, https://github.com/PagerDuty/pagerduty-mcp-server
Keywords: pagerduty,mcp,model-context-protocol,incidents,monitoring,devops
Classifier: Development Status :: 4 - Beta
Classifier: Intended Audience :: Developers
Classifier: Intended Audience :: System Administrators
Classifier: License :: OSI Approved :: Apache Software License
Classifier: Operating System :: OS Independent
Classifier: Programming Language :: Python :: 3
Classifier: Programming Language :: Python :: 3.12
Classifier: Topic :: Software Development :: Libraries :: Python Modules
Classifier: Topic :: System :: Monitoring
Classifier: Topic :: Communications :: Chat
Requires-Python: <3.13,>=3.12
License-File: LICENSE
Requires-Dist: mcp[cli]>=1.8.0
Requires-Dist: pagerduty>=2.0.0
Requires-Dist: typer>=0.16.0
Dynamic: license-file
